MANIFEST.in
README
setup.py
cert/.DS_Store
cert/index.html
cert/mitmproxy.css
tamper/__init__.py
tamper/tamper.py
tamper/version.py
tamper.egg-info/PKG-INFO
tamper.egg-info/SOURCES.txt
tamper.egg-info/dependency_links.txt
tamper.egg-info/requires.txt
tamper.egg-info/top_level.txt